OldStuff/test.v
// module func(out,A,B);
// output out;
// input A, B;
// assign out = (A && (!B)) || ((!A) && B);
// endmodule

// A'B'C + CD'AB + AB
module func2(out, A,B,C,D);
  output out;
  input A,B,C,D;
  wire w1,w2,w3;
  and a1(w1, !A, !B, C);
  and a2(w2, C, !D, A, B);
  and a3(w3, A, B);
  or o1(out, w1,w2,w3);
endmodule

test_tb.v
//testbench
`include "test.v"
module t_func ;
wire t_out;
reg t_A, t_B, t_C, t_D;
parameter stop_time = 160;

func2 F1(t_out, t_A, t_B, t_C, t_D); // Ensure func2 is used instead of func

initial #stop_time $finish;
  initial begin
    $dumpfile("out.vcd");
    $dumpvars(0, t_func);
      t_A = 0; t_B = 0; t_C = 0; t_D = 0;
    #10  t_A = 0; t_B = 0; t_C = 0; t_D = 1;
    #10  t_A = 0; t_B = 0; t_C = 1; t_D = 0;
    #10  t_A = 0; t_B = 0; t_C = 1; t_D = 1;
    #10  t_A = 0; t_B = 1; t_C = 0; t_D = 0;
    #10  t_A = 0; t_B = 1; t_C = 0; t_D = 1;
    #10  t_A = 0; t_B = 1; t_C = 1; t_D = 0;
    #10  t_A = 0; t_B = 1; t_C = 1; t_D = 1;
    #10  t_A = 1; t_B = 0; t_C = 0; t_D = 0;
    #10  t_A = 1; t_B = 0; t_C = 0; t_D = 1;
    #10  t_A = 1; t_B = 0; t_C = 1; t_D = 0;
    #10  t_A = 1; t_B = 0; t_C = 1; t_D = 1;
    #10  t_A = 1; t_B = 1; t_C = 0; t_D = 0;
    #10  t_A = 1; t_B = 1; t_C = 0; t_D = 1;
    #10  t_A = 1; t_B = 1; t_C = 1; t_D = 0;
    #10  t_A = 1; t_B = 1; t_C = 1; t_D = 1;
  end

  initial begin
    $monitor("time = %0d A = %b B = %b C = %b D = %b OUT = %b", $time, t_A, t_B, t_C, t_D, t_out);
  end
endmodule

OldStuff/out.vcd
$date
	Mon Sep 02 01:25:50 2024
$end
$version
	Icarus Verilog
$end
$timescale
	1s
$end
$scope module t_func $end
$var wire 1 ! t_out $end
$var reg 1 " t_A $end
$var reg 1 # t_B $end
$var reg 1 $ t_C $end
$var reg 1 % t_D $end
$scope module F1 $end
$var wire 1 & A $end
$var wire 1 ' B $end
$var wire 1 ( C $end
$var wire 1 ) D $end
$var wire 1 ! out $end
$var wire 1 * w1 $end
$var wire 1 + w2 $end
$var wire 1 , w3 $end
$upscope $end
$upscope $end
$enddefinitions $end
#0
$dumpvars
0,
0+
0*
0)
0(
0'
0&
0%
0$
0#
0"
0!
$end
#10
1%
1)
#20
1!
1*
0%
0)
1$
1(
#30
1%
1)
#40
0!
0*
0%
0)
0$
0(
1#
1'
#50
1%
1)
#60
0%
0)
1$
1(
#70
1%
1)
#80
0%
0)
0$
0(
0#
0'
1"
1&
#90
1%
1)
#100
0%
0)
1$
1(
#110
1%
1)
#120
1!
1,
0%
0)
0$
0(
1#
1'
#130
1%
1)
#140
1+
0%
0)
1$
1(
#150
0+
1%
1)
