OldStuff/adders/halfAdder.v
module half_adder(input A, input B, output C1, output S);
  xor x1(S, A, B);
  and a1(C1, A, B);
endmodule

OldStuff/adders/adder.v
`include "halfAdder.v"
module fullAdder( input A, input B, input Cin, output sum, output Cout );
  wire sum1, carry1, carry2;
  half_adder HA1(.A(A), .B(B), .S(sum1), .C1(carry1));
  half_adder HA2(.A(sum1), .B(Cin), .S(sum), .C1(carry2));
  or o1(Cout, carry1, carry2);
endmodule

OldStuff/adders/fourBitAdder.v
`include "adder.v"
module fourBitAdd(input[3:0] A, input[3:0] B, input Cin, output [3:0] S, output Cout);
  wire C1, C2, C3;

  fullAdder adder0 (.A(A[0]), .B(B[0]), .Cin(Cin), .sum(S[0]), .Cout(C1));

  fullAdder adder1 (.A(A[1]), .B(B[1]), .Cin(C1), .sum(S[1]), .Cout(C2));

  fullAdder adder2 (.A(A[2]), .B(B[2]), .Cin(C2), .sum(S[2]), .Cout(C3));

  fullAdder adder3 (.A(A[3]), .B(B[3]), .Cin(C3), .sum(S[3]), .Cout(Cout));
endmodule

adders/testBenchFourBitAdd.v
`include "fourBitAdder.v"
module tb_fourBitAdd;
  reg [3:0] A, B;        // 4-bit input registers for A and B
  reg Cin;               // Carry-in register
  wire [3:0] S;          // 4-bit output wire for the sum
  wire Cout;             // Carry-out wire

  // Instantiate the fourBitAdd module
  fourBitAdd uut (
    .A(A), 
    .B(B), 
    .Cin(Cin), 
    .S(S), 
    .Cout(Cout)
  );

  initial begin
    $dumpfile("fourBitAdd_tb.vcd"); // Create dump file for GTKWave
    $dumpvars(0, tb_fourBitAdd);    // Dump all variables

    // Apply different test cases
    A = 4'b0000; B = 4'b0000; Cin = 0; #10;  // Test case 1: 0 + 0
    A = 4'b0001; B = 4'b0001; Cin = 0; #10;  // Test case 2: 1 + 1
    A = 4'b0010; B = 4'b0011; Cin = 0; #10;  // Test case 3: 2 + 3
    A = 4'b0101; B = 4'b0101; Cin = 0; #10;  // Test case 4: 5 + 5
    A = 4'b0111; B = 4'b0001; Cin = 1; #10;  // Test case 5: 7 + 1 + carry-in
    A = 4'b1000; B = 4'b1000; Cin = 0; #10;  // Test case 6: 8 + 8
    A = 4'b1111; B = 4'b1111; Cin = 1; #10;  // Test case 7: 15 + 15 + carry-in
    A = 4'b1010; B = 4'b0101; Cin = 0; #10;  // Test case 8: 10 + 5

    $finish; // End the simulation
  end

  // Monitor block to display results
  initial begin
    $monitor("At time %0t: A = %b, B = %b, Cin = %b -> S = %b, Cout = %b", 
             $time, A, B, Cin, S, Cout);
  end
endmodule

OldStuff/adders/fourBitAdd_tb.vcd
$date
	Mon Sep 02 03:50:58 2024
$end
$version
	Icarus Verilog
$end
$timescale
	1s
$end
$scope module tb_fourBitAdd $end
$var wire 1 ! Cout $end
$var wire 4 " S [3:0] $end
$var reg 4 # A [3:0] $end
$var reg 4 $ B [3:0] $end
$var reg 1 % Cin $end
$scope module uut $end
$var wire 4 & A [3:0] $end
$var wire 4 ' B [3:0] $end
$var wire 1 ( C1 $end
$var wire 1 ) C2 $end
$var wire 1 * C3 $end
$var wire 1 + Cin $end
$var wire 1 ! Cout $end
$var wire 4 , S [3:0] $end
$scope module adder0 $end
$var wire 1 - A $end
$var wire 1 . B $end
$var wire 1 + Cin $end
$var wire 1 ( Cout $end
$var wire 1 / carry1 $end
$var wire 1 0 carry2 $end
$var wire 1 1 sum $end
$var wire 1 2 sum1 $end
$scope module HA1 $end
$var wire 1 - A $end
$var wire 1 . B $end
$var wire 1 / C1 $end
$var wire 1 2 S $end
$upscope $end
$scope module HA2 $end
$var wire 1 2 A $end
$var wire 1 + B $end
$var wire 1 0 C1 $end
$var wire 1 1 S $end
$upscope $end
$upscope $end
$scope module adder1 $end
$var wire 1 3 A $end
$var wire 1 4 B $end
$var wire 1 ( Cin $end
$var wire 1 ) Cout $end
$var wire 1 5 carry1 $end
$var wire 1 6 carry2 $end
$var wire 1 7 sum $end
$var wire 1 8 sum1 $end
$scope module HA1 $end
$var wire 1 3 A $end
$var wire 1 4 B $end
$var wire 1 5 C1 $end
$var wire 1 8 S $end
$upscope $end
$scope module HA2 $end
$var wire 1 8 A $end
$var wire 1 ( B $end
$var wire 1 6 C1 $end
$var wire 1 7 S $end
$upscope $end
$upscope $end
$scope module adder2 $end
$var wire 1 9 A $end
$var wire 1 : B $end
$var wire 1 ) Cin $end
$var wire 1 * Cout $end
$var wire 1 ; carry1 $end
$var wire 1 < carry2 $end
$var wire 1 = sum $end
$var wire 1 > sum1 $end
$scope module HA1 $end
$var wire 1 9 A $end
$var wire 1 : B $end
$var wire 1 ; C1 $end
$var wire 1 > S $end
$upscope $end
$scope module HA2 $end
$var wire 1 > A $end
$var wire 1 ) B $end
$var wire 1 < C1 $end
$var wire 1 = S $end
$upscope $end
$upscope $end
$scope module adder3 $end
$var wire 1 ? A $end
$var wire 1 @ B $end
$var wire 1 * Cin $end
$var wire 1 ! Cout $end
$var wire 1 A carry1 $end
$var wire 1 B carry2 $end
$var wire 1 C sum $end
$var wire 1 D sum1 $end
$scope module HA1 $end
$var wire 1 ? A $end
$var wire 1 @ B $end
$var wire 1 A C1 $end
$var wire 1 D S $end
$upscope $end
$scope module HA2 $end
$var wire 1 D A $end
$var wire 1 * B $end
$var wire 1 B C1 $end
$var wire 1 C S $end
$upscope $end
$upscope $end
$upscope $end
$upscope $end
$enddefinitions $end
#0
$dumpvars
0D
0C
0B
0A
0@
0?
0>
0=
0<
0;
0:
09
08
07
06
05
04
03
02
01
00
0/
0.
0-
b0 ,
0+
0*
0)
0(
b0 '
b0 &
0%
b0 $
b0 #
b0 "
0!
$end
#10
17
b10 "
b10 ,
1(
1/
1.
1-
b1 $
b1 '
b1 #
b1 &
#20
07
1=
11
b101 "
b101 ,
0(
1)
12
0/
15
14
0-
13
b11 $
b11 '
b10 #
b10 &
#30
17
0=
1C
01
b1010 "
b1010 ,
1(
0)
1*
02
1/
05
1;
04
1:
1-
03
19
b101 $
b101 '
b101 #
b101 &
#40
1<
1C
1)
0=
1*
07
16
1>
0;
18
11
b1001 "
b1001 ,
0:
13
1%
1+
b1 $
b1 '
b111 #
b111 &
#50
0C
0)
0*
0(
07
06
0=
0<
1!
0/
08
0>
1A
01
b0 "
b0 ,
0.
1@
0-
03
09
1?
0%
0+
b1000 $
b1000 '
b1000 #
b1000 &
#60
17
1=
1C
1(
1)
1*
1/
15
1;
11
b1111 "
b1111 ,
1.
14
1:
1-
13
19
1%
1+
b1111 $
b1111 '
b1111 #
b1111 &
#70
1C
0B
0)
0!
0(
1=
0<
0*
18
05
1D
0A
12
0/
1>
0;
11
b1111 "
b1111 ,
04
0@
0-
09
0%
0+
b101 $
b101 '
b1010 #
b1010 &
