Lab5_Enc_Dec_Latch/encoder.v
module encoder (
  input [7:0] a,
  input en,
  output reg [2:0] out
);
  always @(en,a) begin
    if (a[7] == 1) out =3'b111;
    else if (a[6] == 1) out =3'b110;
    else if (a[5] == 1) out =3'b101;
    else if (a[4] == 1) out =3'b100;
    else if (a[3] == 1) out =3'b011;
    else if (a[2] == 1) out =3'b010;
    else if (a[1] == 1) out =3'b001;
    else if (a[0] == 1) out =3'b000;
    else out = 3'bxxx;
  end
endmodule

Lab5_Enc_Dec_Latch/t_enc.v
`include "encoder.v"
module t_enc;

  reg [7:0] a;
  reg en;
  wire [2:0] out;

  encoder enc(a,en,out);

  initial
    begin
      // $dumpfile("out.vcd");
      // $dumpvars(0, t_enc);
         en=1;a=8'bxxxxxxxx;
      #5 en=1;a=8'b00000001;
      #5 en=1;a=8'b00000010;
      #5 en=1;a=8'b00000100;
      #5 en=1;a=8'b00001000;
      #5 en=1;a=8'b00010000;
      #5 en=1;a=8'b00100000;
      #5 en=1;a=8'b01000000;
      #5 en=1;a=8'b10000000;
      $finish;
    end
  initial
    begin
      $monitor("time=%0d en=%b a=%b out=%b",$time,en,a,out);
    end


endmodule

Lab5_Enc_Dec_Latch/out.vcd
$date
	Wed Sep 18 02:14:36 2024
$end
$version
	Icarus Verilog
$end
$timescale
	1s
$end
$scope module t_enc $end
$var wire 3 ! out [2:0] $end
$var reg 8 " a [7:0] $end
$var reg 1 # en $end
$scope module enc $end
$var wire 8 $ a [7:0] $end
$var wire 1 % en $end
$var reg 3 & out [2:0] $end
$upscope $end
$upscope $end
$enddefinitions $end
#0
$dumpvars
bx &
1%
bx $
1#
bx "
bx !
$end
#5
b0 &
b0 !
b1 "
b1 $
#10
b1 &
b1 !
b10 "
b10 $
#15
b10 &
b10 !
b100 "
b100 $
#20
b11 &
b11 !
b1000 "
b1000 $
#25
b100 &
b100 !
b10000 "
b10000 $
#30
b101 &
b101 !
b100000 "
b100000 $
#35
b110 &
b110 !
b1000000 "
b1000000 $
#40
b111 &
b111 !
b10000000 "
b10000000 $
