Multiplexers/mux2_1.v
//* Make a 4:1 mux using 3 2:1 mux's (AND, NOT, and OR)
//* A0*S' + A1*S

module mux2_1 (
  input [1:0] in, input select, output out
);
  wire a1,a2, n_s;
  not n1(n_s, select);
  and and1(a1, n_s, in[0]);
  and and2(a2, select, in[1]);
  or out1(out, a1,a2);
endmodule

Multiplexers/mux4_1.v
`include "mux2_1.v"

module mux4_1 (
  input [3:0] in,
  input [1:0] select,
  output out);

  wire [1:0] out1;
  mux2_1 mux1(.in(in[3:2]), .select(select[0]), .out(out1[1]));
  mux2_1 mux2(.in(in[1:0]), .select(select[0]), .out(out1[0]));
  mux2_1 mux3(.in(out1[1:0]), .select(select[1]), .out(out));

  // wire a[1:0];
  // mux2_1 m1(.out(a[0]), in[0:1], select[0]);
  // mux2_1 m2(a[1], in[2:3], select[0]);
  // mux2_1 m3(out, a, select[1]);

endmodule

OldStuff/Multiplexers/Mux4_1testbench.v
`include "mux4_1.v"
module testbench();
  // inputs
  reg [3:0] t_in;
  reg [1:0] t_select;

  // output
  wire out;

  mux4_1 m1(t_in, t_select, out);
  initial begin
    $dumpfile("mux4_1testbench.vcd");
    $dumpvars(0, testbench);
        t_in = 4'b0000; t_select = 2'b00;
    #10 t_in = 4'b0001; t_select = 2'b10;
    #10 t_in = 4'b0010; t_select = 2'b01;
    #10 t_in = 4'b0011; t_select = 2'b00;
    #10 t_in = 4'b0100; t_select = 2'b10;
    #10 t_in = 4'b0101; t_select = 2'b01;
    #10 t_in = 4'b0110; t_select = 2'b11;
    #10 t_in = 4'b0111; t_select = 2'b10;
    #10 t_in = 4'b1000; t_select = 2'b01;
    #10 t_in = 4'b1001; t_select = 2'b10;
    #10 t_in = 4'b1010; t_select = 2'b10;
    #10 t_in = 4'b1011; t_select = 2'b01;
    #10 t_in = 4'b1100; t_select = 2'b00;
    #10 t_in = 4'b1101; t_select = 2'b10;
    #10 t_in = 4'b1110; t_select = 2'b00;
    #10 t_in = 4'b1111; t_select = 2'b00;
    #10 $finish;
  end

  initial begin
    $monitor("t_in=%b, t_select=%b, out=%b", t_in, t_select, out);
  end
endmodule

OldStuff/Multiplexers/mux4_1testbench.vcd
$date
	Sun Sep 08 22:36:31 2024
$end
$version
	Icarus Verilog
$end
$timescale
	1s
$end
$scope module testbench $end
$var wire 1 ! out $end
$var reg 4 " t_in [3:0] $end
$var reg 2 # t_select [1:0] $end
$scope module m1 $end
$var wire 4 $ in [3:0] $end
$var wire 1 ! out $end
$var wire 2 % out1 [1:0] $end
$var wire 2 & select [1:0] $end
$scope module mux1 $end
$var wire 1 ' a1 $end
$var wire 1 ( a2 $end
$var wire 2 ) in [1:0] $end
$var wire 1 * n_s $end
$var wire 1 + out $end
$var wire 1 , select $end
$upscope $end
$scope module mux2 $end
$var wire 1 - a1 $end
$var wire 1 . a2 $end
$var wire 2 / in [1:0] $end
$var wire 1 0 n_s $end
$var wire 1 1 out $end
$var wire 1 2 select $end
$upscope $end
$scope module mux3 $end
$var wire 1 3 a1 $end
$var wire 1 4 a2 $end
$var wire 2 5 in [1:0] $end
$var wire 1 6 n_s $end
$var wire 1 ! out $end
$var wire 1 7 select $end
$upscope $end
$upscope $end
$upscope $end
$enddefinitions $end
#0
$dumpvars
07
16
b0 5
04
03
02
01
10
b0 /
0.
0-
0,
0+
1*
b0 )
0(
0'
b0 &
b0 %
b0 $
b0 #
b0 "
0!
$end
#10
11
b1 %
b1 5
1-
06
17
b1 /
b10 #
b10 &
b1 "
b1 $
#20
1!
13
0-
0*
00
1.
16
1,
12
07
b10 /
b1 #
b1 &
b10 "
b10 $
#30
1-
1*
10
0.
0,
02
b11 /
b0 #
b0 &
b11 "
b11 $
#40
14
1!
1+
01
b10 %
b10 5
03
1'
0-
06
17
b1 )
b0 /
b10 #
b10 &
b100 "
b100 $
#50
0+
b0 %
b0 5
0'
0!
0*
00
16
04
1,
12
07
b1 /
b1 #
b1 &
b101 "
b101 $
#60
11
b1 %
b1 5
1.
06
17
b10 /
b11 #
b11 &
b110 "
b110 $
#70
1!
14
1+
b11 %
b11 5
1'
1-
1*
10
0.
0,
02
b11 /
b10 #
b10 &
b111 "
b111 $
#80
01
b10 %
b10 5
03
0!
0'
0-
0*
1(
00
16
04
1,
12
07
b10 )
b0 /
b1 #
b1 &
b1000 "
b1000 $
#90
11
0+
b1 %
b1 5
0!
1-
1*
0(
10
06
04
0,
02
17
b1 /
b10 #
b10 &
b1001 "
b1001 $
#100
01
b0 %
b0 5
0-
b10 /
b1010 "
b1010 $
#110
1!
13
1+
11
b11 %
b11 5
0*
1(
00
1.
16
1,
12
07
b11 /
b1 #
b1 &
b1011 "
b1011 $
#120
0!
03
01
b10 %
b10 5
1'
1*
0(
10
0.
0,
02
b11 )
b0 /
b0 #
b0 &
b1100 "
b1100 $
#130
11
b11 %
b11 5
1!
1-
06
14
17
b1 /
b10 #
b10 &
b1101 "
b1101 $
#140
01
b10 %
b10 5
03
0!
0-
16
04
07
b10 /
b0 #
b0 &
b1110 "
b1110 $
#150
1!
13
11
b11 %
b11 5
1-
b11 /
b1111 "
b1111 $
