OldStuff/lab4/decoder/decoder3_8.v
module decoder3_8 (
  input [2:0] in,
  input enable,
  output [7:0] out
);
  wire n2, n1, n0;

  not no0 (n0, in[0]);
  not no1 (n1, in[1]);
  not no2 (n2, in[2]);

  and a0 (out[0], n2, n1, n0, enable);
  and a1 (out[1], n2, n1, in[0], enable);
  and a2 (out[2], n2, in[1], n0, enable);
  and a3 (out[3], n2, in[1], in[0], enable);
  and a4 (out[4], in[2], n1, n0, enable);
  and a5 (out[5], in[2], n1, in[0], enable);
  and a6 (out[6], in[2], in[1], n0, enable);
  and a7 (out[7], in[2], in[1], in[0], enable);
endmodule

lab4/decoder/decoder4_16.v
`include "decoder3_8.v"

module decoder4_16 (
  input [3:0] in,
  input enable,
  output [15:0] out
);
  wire n_w;
  not not_1(n_w, in[3]);  
  decoder3_8 uut1 (
    .in(in[2:0]),
    .enable(n_w),
    .out(out[7:0])
  );
  decoder3_8 uut2 (
    .in(in[2:0]),
    .enable(in[3]),
    .out(out[15:8])
  );
endmodule

OldStuff/lab4/decoder/decTest.v
`timescale 1ns / 1ps
`include "decoder4_16.v"

module tb_decoder4_16;
  reg [3:0] in;
  reg enable;
  wire [15:0] out;

  // Instantiate the decoder4_16 module
  decoder4_16 uut (
    .in(in),
    .enable(enable),
    .out(out)
  );

  initial begin
    // Initialize inputs
    in = 4'b0000;
    enable = 1'b1;
    #10; // Wait for 10 time units

    in = 4'b0001;
    #10;

    in = 4'b0010;
    #10;

    in = 4'b0011;
    #10;

    in = 4'b0100;
    #10;

    in = 4'b0101;
    #10;

    in = 4'b0110;
    #10;

    in = 4'b0111;
    #10;

    in = 4'b1000;
    #10;

    in = 4'b1001;
    #10;

    in = 4'b1010;
    #10;

    in = 4'b1011;
    #10;

    in = 4'b1100;
    #10;

    in = 4'b1101;
    #10;

    in = 4'b1110;
    #10;

    in = 4'b1111;
    #10;

    $finish; // End the simulation
  end

  initial begin
    $monitor("time = %0d, in = %b, enable = %b, out = %b", $time, in, enable, out);
  end

  initial begin
    $dumpfile("decoder4_16_tb.vcd");
    $dumpvars(0, tb_decoder4_16);
  end
endmodule

OldStuff/lab4/decoder/decoder4_16_tb.vcd
$date
	Mon Sep 09 04:26:29 2024
$end
$version
	Icarus Verilog
$end
$timescale
	1ps
$end
$scope module tb_decoder4_16 $end
$var wire 16 ! out [15:0] $end
$var reg 1 " enable $end
$var reg 4 # in [3:0] $end
$scope module uut $end
$var wire 1 $ enable $end
$var wire 4 % in [3:0] $end
$var wire 1 & n_w $end
$var wire 16 ' out [15:0] $end
$scope module uut1 $end
$var wire 1 & enable $end
$var wire 3 ( in [2:0] $end
$var wire 1 ) n0 $end
$var wire 1 * n1 $end
$var wire 1 + n2 $end
$var wire 8 , out [7:0] $end
$upscope $end
$scope module uut2 $end
$var wire 1 - enable $end
$var wire 3 . in [2:0] $end
$var wire 1 / n0 $end
$var wire 1 0 n1 $end
$var wire 1 1 n2 $end
$var wire 8 2 out [7:0] $end
$upscope $end
$upscope $end
$upscope $end
$enddefinitions $end
#0
$dumpvars
b0 2
11
10
1/
b0 .
0-
b1 ,
1+
1*
1)
b0 (
b1 '
1&
b0 %
1$
b0 #
1"
b1 !
$end
#10000
0)
b10 !
b10 '
b10 ,
0/
b1 (
b1 .
b1 #
b1 %
#20000
1)
0*
b100 !
b100 '
b100 ,
1/
00
b10 (
b10 .
b10 #
b10 %
#30000
0)
b1000 !
b1000 '
b1000 ,
0/
b11 (
b11 .
b11 #
b11 %
#40000
1)
1*
0+
b10000 !
b10000 '
b10000 ,
1/
10
01
b100 (
b100 .
b100 #
b100 %
#50000
0)
b100000 !
b100000 '
b100000 ,
0/
b101 (
b101 .
b101 #
b101 %
#60000
1)
0*
b1000000 !
b1000000 '
b1000000 ,
1/
00
b110 (
b110 .
b110 #
b110 %
#70000
0)
b10000000 !
b10000000 '
b10000000 ,
0/
b111 (
b111 .
b111 #
b111 %
#80000
1)
1*
1+
b0 ,
1/
10
11
0&
b100000000 !
b100000000 '
b1 2
b0 (
b0 .
1-
b1000 #
b1000 %
#90000
0)
0/
b1000000000 !
b1000000000 '
b10 2
b1 (
b1 .
b1001 #
b1001 %
#100000
1)
0*
1/
00
b10000000000 !
b10000000000 '
b100 2
b10 (
b10 .
b1010 #
b1010 %
#110000
0)
0/
b100000000000 !
b100000000000 '
b1000 2
b11 (
b11 .
b1011 #
b1011 %
#120000
1)
1*
0+
1/
10
01
b1000000000000 !
b1000000000000 '
b10000 2
b100 (
b100 .
b1100 #
b1100 %
#130000
0)
0/
b10000000000000 !
b10000000000000 '
b100000 2
b101 (
b101 .
b1101 #
b1101 %
#140000
1)
0*
1/
00
b100000000000000 !
b100000000000000 '
b1000000 2
b110 (
b110 .
b1110 #
b1110 %
#150000
0)
0/
b1000000000000000 !
b1000000000000000 '
b10000000 2
b111 (
b111 .
b1111 #
b1111 %
