Tutorial/Tutorail Flip Flops/dff.v
module dff (
    input clk,
    input d,
    output reg q
);
    always @(posedge clk) begin
        q<=d;
    end
endmodule

DD F215 Verilog Tutorial Questions/DD F215 Verilog Flip Flop/testbench_dff.v
`include "dff.v"
module dff_tb;
    reg clk, d;
    wire q;

    dff dut (
        .clk(clk),
        .d(d),
        .q(q)
    );

    // Clock generation
    always begin
        #5 clk = ~clk;
    end

    // Testbench stimulus
    initial begin
        $dumpfile("dff_tb.vcd");
        $dumpvars(0, dff_tb);

        clk = 0;
        d = 0;

        #10 d = 1;
        #10 d = 0;
        #10 d = 1;
        #10 d = 0;

        #20 $finish;
    end
endmodule

Tutorial/Tutorail Flip Flops/dff_tb.vcd
$date
	Tue Sep 17 18:07:51 2024
$end
$version
	Icarus Verilog
$end
$timescale
	1s
$end
$scope module dff_tb $end
$var wire 1 ! q $end
$var reg 1 " clk $end
$var reg 1 # d $end
$scope module dut $end
$var wire 1 " clk $end
$var wire 1 # d $end
$var reg 1 ! q $end
$upscope $end
$upscope $end
$enddefinitions $end
$comment Show the parameter values. $end
$dumpall
$end
#0
$dumpvars
0#
0"
x!
$end
#5
0!
1"
#10
0"
1#
#15
1!
1"
#20
0"
0#
#25
0!
1"
#30
0"
1#
#35
1!
1"
#40
0"
0#
#45
0!
1"
