Tutorial/Tutorail Flip Flops/dff_asycr.v
// File: dff_async_reset.v
module dff_async_reset (
    input clk,
    input reset,
    input d,
    output reg q
);
    always @(posedge clk or posedge reset) begin
        if (reset==1'b1) q<=1'b0;
        else q<=d;
    end
endmodule

Tutorial/Tutorail Flip Flops/testbench_dff_asycr.v
`include "dff_asycr.v"
module dff_async_reset_tb;
    reg clk, reset, d;
    wire q;

    dff_async_reset dut (
        .clk(clk),
        .reset(reset),
        .d(d),
        .q(q)
    );

    // Clock generation
    always begin
        #5 clk = ~clk;
    end

    // Testbench stimulus
    initial begin
        $dumpfile("dff_async_reset_tb.vcd");
        $dumpvars(0, dff_async_reset_tb);

        clk = 0;
        reset = 0;
        d = 0;

        #10 d = 1;
        #10 d = 0;
        #10 d = 1;

        #7 reset = 1;  // Asynchronous reset
        #6 reset = 0;

        #10 d = 0;
        #10 d = 1;

        #20 $finish;
    end
endmodule

Tutorial/Tutorail Flip Flops/dff_async_reset_tb.vcd
$date
	Tue Sep 17 18:12:17 2024
$end
$version
	Icarus Verilog
$end
$timescale
	1s
$end
$scope module dff_async_reset_tb $end
$var wire 1 ! q $end
$var reg 1 " clk $end
$var reg 1 # d $end
$var reg 1 $ reset $end
$scope module dut $end
$var wire 1 " clk $end
$var wire 1 # d $end
$var wire 1 $ reset $end
$var reg 1 ! q $end
$upscope $end
$upscope $end
$enddefinitions $end
$comment Show the parameter values. $end
$dumpall
$end
#0
$dumpvars
0$
0#
0"
x!
$end
#5
0!
1"
#10
0"
1#
#15
1!
1"
#20
0"
0#
#25
0!
1"
#30
0"
1#
#35
1!
1"
#37
0!
1$
#40
0"
#43
0$
#45
1!
1"
#50
0"
#53
0#
#55
0!
1"
#60
0"
#63
1#
#65
1!
1"
