Tutorial/Tutorail Flip Flops/dff_sycr.v
module dff_sync_reset (
    input clk,
    input reset,
    input d,
    output reg q
);
    always @(posedge clk) begin
        if (reset==1'b1) q<=1'b0;
        else q<=d;
    end
    
endmodule

DD F215 Verilog Tutorial Questions/DD F215 Verilog Flip Flop/testbench_dff_sycr.v
`include "dff_sycr.v"
module dff_sync_reset_tb;
    reg clk, reset, d;
    wire q;

    dff_sync_reset dut (
        .clk(clk),
        .reset(reset),
        .d(d),
        .q(q)
    );

    // Clock generation
    always begin
        #5 clk = ~clk;
    end

    // Testbench stimulus
    initial begin
        $dumpfile("dff_sync_reset_tb.vcd");
        $dumpvars(0, dff_sync_reset_tb);

        clk = 0;
        reset = 0;
        d = 0;

        #10 d = 1;
        #10 d = 0;
        #10 d = 1;

        #10 reset = 1;
        #10 reset = 0;

        #10 d = 0;
        #10 d = 1;

        #20 $finish;
    end
endmodule

Tutorial/Tutorail Flip Flops/dff_sync_reset_tb.vcd
$date
	Thu Sep 19 08:26:44 2024
$end
$version
	Icarus Verilog
$end
$timescale
	1s
$end
$scope module dff_sync_reset_tb $end
$var wire 1 ! q $end
$var reg 1 " clk $end
$var reg 1 # d $end
$var reg 1 $ reset $end
$scope module dut $end
$var wire 1 % clk $end
$var wire 1 & d $end
$var wire 1 ' reset $end
$var reg 1 ( q $end
$upscope $end
$upscope $end
$enddefinitions $end
#0
$dumpvars
x(
0'
0&
0%
0$
0#
0"
x!
$end
#5
0(
0!
1"
1%
#10
0"
0%
1#
1&
#15
1(
1!
1"
1%
#20
0"
0%
0#
0&
#25
0(
0!
1"
1%
#30
0"
0%
1#
1&
#35
1(
1!
1"
1%
#40
0"
0%
1$
1'
#45
0(
0!
1"
1%
#50
0"
0%
0$
0'
#55
1(
1!
1"
1%
#60
0"
0%
0#
0&
#65
0(
0!
1"
1%
#70
0"
0%
1#
1&
#75
1(
1!
1"
1%
