lab4/decoder3_8/decoder3_8.v
module decoder3_8 (
  input [2:0] in,
  output [7:0] out
);
  // wire d0,d1,d2,d3,d4,d5,d6,d7;
  wire n2,n1,n0;

  not no0 (n0, in[0]);
  not no1 (n1, in[1]);
  not no2 (n2, in[2]);

  and a0 (out[0], n2, n1, n0);
  and a1 (out[1], n2, n1, in[0]);
  and a2 (out[2], n2, in[1], n0);
  and a3 (out[3], n2, in[1], in[0]);
  and a4 (out[4], in[2], n1, n0);
  and a5 (out[5], in[2], n1, in[0]);
  and a6 (out[6], in[2], in[1], n0);
  and a7 (out[7], in[2], in[1], in[0]);
endmodule

lab4/decoder3_8/decTest.v
`timescale 1ns / 1ps
`include "decoder3_8.v"

module tb_decoder3_8;
  reg [2:0] in;
  wire [7:0] out;

  // Instantiate the decoder3_8 module
  decoder3_8 uut (
    .in(in),
    .out(out)
  );

  initial begin
    // Initialize inputs
    in = 3'b000;
    #10; // Wait for 10 time units

    in = 3'b001;
    #10;

    in = 3'b010;
    #10;

    in = 3'b011;
    #10;

    in = 3'b100;
    #10;

    in = 3'b101;
    #10;

    in = 3'b110;
    #10;

    in = 3'b111;
    #10;

    $finish; // End the simulation
  end

  initial begin
    $monitor("time = %0d, in = %b, out = %b", $time, in, out);
  end

  initial begin
    $dumpfile("decoder3_8_tb.vcd");
    $dumpvars(0, tb_decoder3_8);
  end
endmodule

lab4/decoder3_8/decoder3_8_tb.vcd
$date
	Mon Sep 09 04:01:08 2024
$end
$version
	Icarus Verilog
$end
$timescale
	1ps
$end
$scope module tb_decoder3_8 $end
$var wire 8 ! out [7:0] $end
$var reg 3 " in [2:0] $end
$scope module uut $end
$var wire 3 # in [2:0] $end
$var wire 1 $ n0 $end
$var wire 1 % n1 $end
$var wire 1 & n2 $end
$var wire 8 ' out [7:0] $end
$upscope $end
$upscope $end
$enddefinitions $end
#0
$dumpvars
b1 '
1&
1%
1$
b0 #
b0 "
b1 !
$end
#10000
0$
b10 !
b10 '
b1 "
b1 #
#20000
1$
0%
b100 !
b100 '
b10 "
b10 #
#30000
0$
b1000 !
b1000 '
b11 "
b11 #
#40000
1$
1%
0&
b10000 !
b10000 '
b100 "
b100 #
#50000
0$
b100000 !
b100000 '
b101 "
b101 #
#60000
1$
0%
b1000000 !
b1000000 '
b110 "
b110 #
#70000
0$
b10000000 !
b10000000 '
b111 "
b111 #
